Metadata-Version: 2.1
Name: playstore-scraper
Version: 1.0.0
Summary: A python library to scrape data on playstore automatically.
Home-page: https://datakund.com
Author: DataKund
Author-email: datakund@gmail.com
License: Apache License 2.0
Keywords: playstore python bot_studio scraper data web-scraping
Platform: UNKNOWN
